agenshindot/__init__.py
agenshindot/__main__.py
agenshindot/config.py
agenshindot/database/__init__.py
agenshindot/database/action/__init__.py
agenshindot/database/action/id_and_cookie.py
agenshindot/database/engine.py
agenshindot/database/model/__init__.py
agenshindot/database/model/id_and_cookie.py
agenshindot/log.py
agenshindot/main.py
agenshindot/modules/bind.py
agenshindot/modules/check_cookie.py
agenshindot/modules/console.py
agenshindot/modules/mihoyo_bbs/__init__.py
agenshindot/modules/mihoyo_bbs/data.py
agenshindot/modules/mihoyo_bbs/draw.py
agenshindot/modules/wiki/__init__.py
agenshindot/modules/wiki/data.py
agenshindot/resource/mihoyo_bbs/anemoculus.png
agenshindot/resource/mihoyo_bbs/chest.png
agenshindot/resource/mihoyo_bbs/constellation.png
agenshindot/resource/mihoyo_bbs/currency.png
agenshindot/resource/mihoyo_bbs/electroculus.png
agenshindot/resource/mihoyo_bbs/fetter.png
agenshindot/resource/mihoyo_bbs/geoculus.png
agenshindot/resource/mihoyo_bbs/goto.png
agenshindot/resource/mihoyo_bbs/HYWH85W.ttf
agenshindot/resource/mihoyo_bbs/star.png
agenshindot/resource/mihoyo_bbs/visitor.png
agenshindot/typing.py
agenshindot/utils/__init__.py
agenshindot/utils/img.py
agenshindot/utils/mihoyo_bbs/__init__.py
agenshindot/utils/mihoyo_bbs/base.py
agenshindot/utils/mihoyo_bbs/model/__init__.py
agenshindot/utils/mihoyo_bbs/model/base.py
agenshindot/utils/mihoyo_bbs/request.py
agenshindot/utils/minigg/__init__.py
agenshindot/utils/minigg/character.py
agenshindot/utils/minigg/exception.py
agenshindot/utils/minigg/model/__init__.py
agenshindot/utils/minigg/model/character.py
agenshindot/utils/minigg/model/other.py
agenshindot/utils/minigg/model/talent.py
agenshindot/utils/minigg/model/weapon.py
agenshindot/utils/minigg/other.py
agenshindot/utils/minigg/weapon.py
agenshindot/utils/msg.py
agenshindot/version.py
agenshindot-0.2.0.dist-info/LICENSE
agenshindot-0.2.0.dist-info/WHEEL
agenshindot-0.2.0.dist-info/METADATA
agenshindot-0.2.0.dist-info/RECORD
