Metadata-Version: 2.1
Name: agenshindot
Version: 0.2.0
Summary: GenshinDot for Python, powered by Graia-Ariadne.
Home-page: https://github.com/MingxuanGame/AGenshinDot
License: AGPL-3.0-or-later
Author: MingxuanGame
Author-email: MingxuanGame@outlook.com
Requires-Python: >=3.8,<4.0
Classifier: License :: OSI Approved :: GNU Affero General Public License v3 or later (AGPLv3+)
Classifier: Programming Language :: Python :: 3
Classifier: Programming Language :: Python :: 3.10
Classifier: Programming Language :: Python :: 3.8
Classifier: Programming Language :: Python :: 3.9
Requires-Dist: Pillow (>=9.2.0,<10.0.0)
Requires-Dist: SQLAlchemy (>=1.4.39,<2.0.0)
Requires-Dist: aiosqlite (>=0.17.0,<0.18.0)
Requires-Dist: graia-ariadne[standard] (>=0.8.1,<0.9.0)
Requires-Dist: prompt-toolkit (>=3.0.30,<4.0.0)
Requires-Dist: tomlkit (>=0.11.2,<0.12.0)
Project-URL: Documentation, https://github.com/MingxuanGame/AGenshinDot
Project-URL: Repository, https://github.com/MingxuanGame/AGenshinDot
